{
  "contents": [
    [
      "backpack",
      1
    ],
    [
      "blanket",
      1
    ],
    [
      "holy-water",
      1
    ],
    [
      "rations",
      2
    ],
    [
      "tinderbox",
      1
    ],
    [
      "candle",
      10
    ],
    [
      "waterskin",
      1
    ]
  ],
  "description": "A religious kit containing ceremonial supplies and basic adventuring gear for traveling clergy. Unpacking equips a backpack and places all contents inside it.",
  "id": "priests-pack",
  "image": "/res/img/items/priests-pack.png",
  "name": "Priest's Pack",
  "notes": [],
  "value": 2830,
  "rarity": "common",
  "stack": 1,
  "tags": [
    "pack"
  ],
  "type": "Pack",
  "weight": 29
}
