{
  "id": "very-tired",
  "name": "Very Tired",
  "description": "Getting very tired. Reduced dexterity and constitution.",
  "source_type": "system_status",
  "category": "debuff",
  "removal": {
    "type": "conditional",
    "condition": "fatigue != 8"
  },
  "system_check": {
    "stat": "fatigue",
    "operator": "==",
    "value": 8
  },
  "modifiers": [
    {
      "stat": "dexterity",
      "value": -2,
      "type": "constant"
    },
    {
      "stat": "strength",
      "value": -1,
      "type": "constant"
    }
  ],
  "message": "You're getting very tired and need rest soon.",
  "visible": true
}