{
  "name": "Fire Bolt",
  "description": "You hurl a mote of fire at a creature or object within range. Make a ranged spell attack against the target. On a hit, the target takes 1d10 fire damage. A flammable object hit by this spell ignites if it isn't being worn or carried.",
  "level": 0,
  "school": "evocation",
  "casting_time": "action",
  "range": "4",
  "range_long": "6",
  "duration": "instantaneous",
  "concentration": false,
  "damage": "1d10",
  "damage_type": "fire",
  "heal": null,
  "effect": null,
  "type": "Spell",
  "spell_attack": "ranged",
  "save_type": null,
  "tags": [
    "combat",
    "damage",
    "ranged",
    "fire",
    "cantrip"
  ],
  "classes": [
    "sorcerer",
    "wizard",
    "artificer"
  ],
  "rarity": "common",
  "action_cost": "action",
  "mana_cost": 2,
  "notes": [
    "Highest damage cantrip alongside Eldritch Blast (1d10 fire) — fire is the more resisted damage type",
    "Can ignite flammable objects"
  ],
  "material_component": {
    "required": [],
    "focus_provided": ""
  }
}
