{
  "name": "Poison Spray",
  "description": "You extend your hand toward a creature you can see within range and project a puff of noxious gas from your palm. The creature must succeed on a Constitution saving throw or take 1d12 poison damage.",
  "level": 0,
  "school": "conjuration",
  "casting_time": "action",
  "range": "1",
  "range_long": "1",
  "duration": "instantaneous",
  "concentration": false,
  "damage": "1d12",
  "damage_type": "poison",
  "heal": null,
  "effect": null,
  "type": "Spell",
  "spell_attack": null,
  "save_type": "constitution",
  "tags": [
    "combat",
    "damage",
    "poison",
    "cantrip"
  ],
  "classes": [
    "druid",
    "sorcerer",
    "warlock",
    "wizard",
    "artificer"
  ],
  "rarity": "common",
  "action_cost": "action",
  "mana_cost": 1,
  "notes": [
    "Highest damage die of any cantrip (1d12) but extremely short range (10 feet) and many creatures resist poison",
    "High risk/reward: close range + common resistance"
  ],
  "material_component": {
    "required": [],
    "focus_provided": ""
  }
}
